phicite_python_client/__init__.py
phicite_python_client/client.py
phicite_python_client-0.1.0.dist-info/METADATA
phicite_python_client-0.1.0.dist-info/WHEEL
phicite_python_client-0.1.0.dist-info/RECORD
