Metadata-Version: 2.3
Name: phicite-python-client
Version: 0.1.0
Summary: 
Author: Paul Adamson
Author-email: paul.adamson.01@gmail.com
Requires-Python: >=3.12
Classifier: Programming Language :: Python :: 3
Classifier: Programming Language :: Python :: 3.12
Classifier: Programming Language :: Python :: 3.13
Requires-Dist: requests (>=2.32.3,<3.0.0)
